LICENSE
README.md
README.rst
setup.py
metacrafter/__init__.py
metacrafter/__main__.py
metacrafter/core.py
metacrafter.egg-info/PKG-INFO
metacrafter.egg-info/SOURCES.txt
metacrafter.egg-info/dependency_links.txt
metacrafter.egg-info/entry_points.txt
metacrafter.egg-info/not-zip-safe
metacrafter.egg-info/requires.txt
metacrafter.egg-info/top_level.txt
metacrafter/classify/__init__.py
metacrafter/classify/processor.py
metacrafter/classify/stats.py
metacrafter/classify/utils.py
metacrafter/registry/__init__.py
metacrafter/registry/client.py
metacrafter/server/__init__.py
metacrafter/server/api.py
metacrafter/server/manager.py