Metadata-Version: 2.1
Name: metacrafter
Version: 0.0.4
Summary: Metacrafter metadata classification tool
Home-page: https://github.com/apicrafter/metacrafter/
Download-URL: https://github.com/apicrafter/metacrafter/
Author: Ivan Begtin
Author-email: ivan@begtin.tech
License: Apache
Keywords: json jsonl csv bson cli dataset metadata
Classifier: Development Status :: 5 - Production/Stable
Classifier: Programming Language :: Python
Classifier: Programming Language :: Python :: 3 :: Only
Classifier: Programming Language :: Python :: 3.6
Classifier: Programming Language :: Python :: 3.7
Classifier: Programming Language :: Python :: 3.8
Classifier: Programming Language :: Python :: 3.9
Classifier: Environment :: Console
Classifier: Intended Audience :: Developers
Classifier: Intended Audience :: System Administrators
Classifier: License :: OSI Approved :: BSD License
Classifier: Topic :: Software Development
Classifier: Topic :: System :: Networking
Classifier: Topic :: Terminals
Classifier: Topic :: Text Processing
Classifier: Topic :: Utilities
License-File: LICENSE
